ai/__init__.py
ai/solve.py
jetha_ai-1.dist-info/METADATA
jetha_ai-1.dist-info/WHEEL
jetha_ai-1.dist-info/top_level.txt
jetha_ai-1.dist-info/RECORD
